gensyncio/__init__.py
gensyncio/exceptions.py
gensyncio/future.py
gensyncio/gensocket.py
gensyncio/globs.py
gensyncio/http/__init__.py
gensyncio/http/client.py
gensyncio/http/parser.py
gensyncio/http/server.py
gensyncio/http/utils.py
gensyncio/loop.py
gensyncio/queue.py
gensyncio/sync.py
gensyncio/task.py
gensyncio/utils.py
gensyncio-1.0.0.dist-info/METADATA
gensyncio-1.0.0.dist-info/WHEEL
gensyncio-1.0.0.dist-info/RECORD
